tansu/events/__init__.py
tansu/events/consume.py
tansu/events/ingest.py
tansu/events/log.py
tansu/events/models.py
tansu/events/settings.py
tansu/events/database/__init__.py
tansu/events/database/db_models.py
tansu/events/database/session_factory.py
tansu-1.0.1.dist-info/METADATA
tansu-1.0.1.dist-info/WHEEL
tansu-1.0.1.dist-info/RECORD
