Metadata-Version: 2.3
Name: tansu
Version: 1.0.1
Summary: Tansu - Soroban Versioning
Project-URL: homepage, https://github.com/tupui/soroban-versioning
Project-URL: documentation, https://github.com/tupui/soroban-versioning
Project-URL: source, https://github.com/tupui/soroban-versioning
Author: Pamphile Roy
Maintainer: Tansu contributors
License-Expression: BSD-3-Clause
Keywords: blockchain,cryptocurrency,git,soroban,soroban-rpc,stellar,stellar.org
Classifier: Development Status :: 4 - Beta
Classifier: Intended Audience :: Developers
Classifier: License :: OSI Approved :: BSD License
Classifier: Operating System :: OS Independent
Classifier: Programming Language :: Python
Classifier: Programming Language :: Python :: 3
Classifier: Programming Language :: Python :: 3.12
Requires-Python: >=3.12
Requires-Dist: alembic[tz]
Requires-Dist: pydantic
Requires-Dist: pydantic-settings
Requires-Dist: sqlalchemy[postgresql-asyncpg,postgresql-psycopgbinary]
Requires-Dist: stellar-sdk
Provides-Extra: dev
Requires-Dist: hatch; extra == 'dev'
Requires-Dist: locust; extra == 'dev'
Requires-Dist: pre-commit; extra == 'dev'
Requires-Dist: pytest; extra == 'dev'
Requires-Dist: pytest-asyncio; extra == 'dev'
Requires-Dist: ruff; extra == 'dev'
Provides-Extra: test
Requires-Dist: locust; extra == 'test'
Requires-Dist: pytest; extra == 'test'
Requires-Dist: pytest-asyncio; extra == 'test'
